midas_palaestrai/__init__.py
midas_palaestrai/arl_attacker_objective.py
midas_palaestrai/arl_collector.py
midas_palaestrai/arl_defender_objective.py
midas_palaestrai/database_view.py
midas_palaestrai/descriptor.py
midas_palaestrai/gauss.py
midas_palaestrai/objectives.py
midas_palaestrai/query.py
midas_palaestrai/reactive_power_muscle.py
midas_palaestrai/reward.py
midas_palaestrai/rewards.py
midas_palaestrai/voltage_attacker_objective.py
midas_palaestrai/voltage_defender_objective.py
midas_palaestrai-3.5.8.dist-info/licenses/LICENSE
midas_palaestrai-3.5.8.dist-info/METADATA
midas_palaestrai-3.5.8.dist-info/WHEEL
midas_palaestrai-3.5.8.dist-info/top_level.txt
midas_palaestrai-3.5.8.dist-info/RECORD
