Metadata-Version: 2.4
Name: midas_palaestrai
Version: 3.5.8
Summary: This package contains everything needed to use midas with palaestrAI.
Author-email: The ARL Developers <stephan.balduin@offis.de>
Project-URL: Homepage, https://gitlab.com/midas-mosaik/midas-palaestrai
Project-URL: Documentation, https://midas-mosaik.gitlab.io/midas
Project-URL: Bug Tracker, https://gitlab.com/midas-mosaik/midas-palaestrai/-/issues
Classifier: Development Status :: 4 - Beta
Classifier: Intended Audience :: Science/Research
Classifier: License :: OSI Approved :: GNU Lesser General Public License v2 (LGPLv2)
Classifier: Natural Language :: English
Classifier: Operating System :: OS Independent
Classifier: Programming Language :: Python
Classifier: Programming Language :: Python :: 3
Classifier: Programming Language :: Python :: 3.10
Classifier: Programming Language :: Python :: 3.11
Classifier: Programming Language :: Python :: 3.12
Classifier: Topic :: Scientific/Engineering
Classifier: Topic :: Software Development :: Libraries :: Python Modules
Requires-Python: >=3.10
License-File: LICENSE
Requires-Dist: funcy
Requires-Dist: midas-mosaik>=2.0.2
Requires-Dist: mosaik_api
Provides-Extra: arl
Requires-Dist: palaestrai-mosaik>=3.5.6; extra == "arl"
Requires-Dist: palaestrai>=3.5.6; extra == "arl"
Provides-Extra: dev
Requires-Dist: mypy~=1.0.1; extra == "dev"
Requires-Dist: pytest; extra == "dev"
Requires-Dist: coverage; extra == "dev"
Requires-Dist: black~=24.1.0; extra == "dev"
Requires-Dist: setuptools; extra == "dev"
Requires-Dist: twine; extra == "dev"
Requires-Dist: wheel; extra == "dev"
Requires-Dist: pandapower; extra == "dev"
Requires-Dist: palaestrai>=3.5.6; extra == "dev"
Requires-Dist: midas-mosaik[base]>=2.0.2; extra == "dev"
Requires-Dist: mosaik; extra == "dev"
Dynamic: license-file
